hmd_lib_auth/__init__.py
hmd_lib_auth/hmd_lib_auth.py
hmd_lib_auth/lambda_helper.py
hmd_lib_auth/open_policy_agent.py
hmd_lib_auth-0.1.116.dist-info/METADATA
hmd_lib_auth-0.1.116.dist-info/WHEEL
hmd_lib_auth-0.1.116.dist-info/top_level.txt
hmd_lib_auth-0.1.116.dist-info/RECORD
